minilayer/__init__.py
minilayer/__main__.py
minilayer/py.typed
minilayer/cli/__init__.py
minilayer/cli/generate.py
minilayer/cli/install.py
minilayer/devcontainer/__init__.py
minilayer/devcontainer/feature_generation/__init__.py
minilayer/devcontainer/feature_generation/oci_feature_generator.py
minilayer/devcontainer/models/__init__.py
minilayer/devcontainer/models/devcontainer_feature_definition.py
minilayer/installers/__init__.py
minilayer/installers/apt/__init__.py
minilayer/installers/apt/apt_installer.py
minilayer/installers/apt_get/__init__.py
minilayer/installers/apt_get/apt_get_installer.py
minilayer/installers/aptitude/__init__.py
minilayer/installers/aptitude/aptitude_installer.py
minilayer/installers/devcontainer_feature/__init__.py
minilayer/installers/devcontainer_feature/oci_feature.py
minilayer/installers/devcontainer_feature/oci_feature_installer.py
minilayer/installers/devcontainer_feature/models/__init__.py
minilayer/installers/devcontainer_feature/models/devcontainer_feature.py
minilayer/installers/gh_release/__init__.py
minilayer/installers/gh_release/gh_release_installer.py
minilayer/utils/__init__.py
minilayer/utils/invoker.py
minilayer/utils/linux_information_desk.py
minilayer/utils/oci_registry.py
minilayer/utils/settings.py
minilayer/utils/version.py
minilayer-0.3.7.dist-info/METADATA
minilayer-0.3.7.dist-info/WHEEL
minilayer-0.3.7.dist-info/entry_points.txt
minilayer-0.3.7.dist-info/top_level.txt
minilayer-0.3.7.dist-info/RECORD
