Metadata-Version: 2.1
Name: minilayer
Version: 0.3.7
Author: Daniel Braun
Requires-Dist: pydantic (==1.10.5)
Requires-Dist: typer
Requires-Dist: invoke
Requires-Dist: semver (==2.13.0)
Provides-Extra: dev
Requires-Dist: pytest ; extra == 'dev'
Requires-Dist: pytest-shell-utilities ; extra == 'dev'
Requires-Dist: black ; extra == 'dev'
Requires-Dist: mypy ; extra == 'dev'
Requires-Dist: gitpython ; extra == 'dev'
Requires-Dist: build ; extra == 'dev'
Requires-Dist: setuptools ; extra == 'dev'
Requires-Dist: wheel ; extra == 'dev'
Requires-Dist: setuptools-scm ; extra == 'dev'
Requires-Dist: packaging ; extra == 'dev'
Provides-Extra: generate
Requires-Dist: easyfs (==0.0.3) ; extra == 'generate'
